[
    {"brand":"Reformation", "img":"./img/Reformation.png", "alt":"Reformation brand", "url":"https://www.thereformation.com/"},
    {"brand":"Outerknown", "img":"./img/Outerknown.png", "alt":"Outerknown brand", "url":"https://www.outerknown.com/"},
    {"brand":"KOTN", "img":"./img/KOTN.png", "alt":"KOTN brand", "url":"https://kotn.com/"},
    {"brand":"Quince", "img":"./img/Quince.png", "alt":"Quince brand", "url":"https://www.onequince.com/"},
    {"brand":"ABLE", "img":"./img/ABLE.png", "alt":"ABLE brand", "url":"https://www.ableclothing.com/"},
    {"brand":"Aday", "img":"./img/Aday.png", "alt":"Aday brand", "url":"https://www.thisisaday.com/"},
    {"brand":"Sezane", "img":"./img/Sezane.png", "alt":"Sezane brand", "url":"https://www.sezane.com/us"},
    {"brand":"Vetta", "img":"./img/Vetta.png", "alt":"Vetta brand", "url":"https://www.vettacapsule.com/"},
    {"brand":"Boden", "img":"./img/Boden.png", "alt":"Boden brand", "url":"https://www.bodenusa.com/en-us"},
    {"brand":"Toad&Co", "img":"./img/Toad&Co.png", "alt":"Toad&Co brand", "url":"https://www.toadandco.com/"},
    {"brand":"Nube", "img":"./img/Nube.png", "alt":"Nube brand", "url":"https://nubeusa.com/"},
    {"brand":"Katla", "img":"./img/Katla.png", "alt":"Katla brand", "url":"https://katla.com/"}
]